odoo/addons/sale_order_import_ubl_http/README.rst
odoo/addons/sale_order_import_ubl_http/__init__.py
odoo/addons/sale_order_import_ubl_http/__manifest__.py
odoo/addons/sale_order_import_ubl_http/controllers/__init__.py
odoo/addons/sale_order_import_ubl_http/controllers/main.py
odoo/addons/sale_order_import_ubl_http/data/queue_job_channel.xml
odoo/addons/sale_order_import_ubl_http/data/queue_job_function.xml
odoo/addons/sale_order_import_ubl_http/data/res_users.xml
odoo/addons/sale_order_import_ubl_http/i18n/sale_order_import_ubl_http.pot
odoo/addons/sale_order_import_ubl_http/models/__init__.py
odoo/addons/sale_order_import_ubl_http/models/res_company.py
odoo/addons/sale_order_import_ubl_http/models/res_config_settings.py
odoo/addons/sale_order_import_ubl_http/models/sale_order.py
odoo/addons/sale_order_import_ubl_http/readme/CONTRIBUTORS.rst
odoo/addons/sale_order_import_ubl_http/readme/DESCRIPTION.rst
odoo/addons/sale_order_import_ubl_http/readme/USAGE.rst
odoo/addons/sale_order_import_ubl_http/static/description/icon.png
odoo/addons/sale_order_import_ubl_http/static/description/index.html
odoo/addons/sale_order_import_ubl_http/tests/__init__.py
odoo/addons/sale_order_import_ubl_http/tests/test_sale_order_import_endpoint.py
odoo/addons/sale_order_import_ubl_http/tests/examples/UBL-Order-2.0-Example.xml
odoo/addons/sale_order_import_ubl_http/views/res_config_settings.xml
odoo13_addon_sale_order_import_ubl_http-13.0.1.1.3.dist-info/METADATA
odoo13_addon_sale_order_import_ubl_http-13.0.1.1.3.dist-info/WHEEL
odoo13_addon_sale_order_import_ubl_http-13.0.1.1.3.dist-info/top_level.txt
odoo13_addon_sale_order_import_ubl_http-13.0.1.1.3.dist-info/RECORD
