Metadata-Version: 2.1
Name: odoo13-addon-sale-order-import-ubl-http
Version: 13.0.1.1.3
Summary: Add an HTTP endpoint to import UBL formatted ordersautomatically as sales order
Home-page: https://github.com/OCA/edi
Author: Camptocamp,Odoo Community Association (OCA)
Author-email: support@odoo-community.org
License: AGPL-3
Platform: UNKNOWN
Classifier: Programming Language :: Python
Classifier: Framework :: Odoo
Classifier: Framework :: Odoo :: 13.0
Classifier: License :: OSI Approved :: GNU Affero General Public License v3
Requires-Python: >=3.5
Requires-Dist: odoo13-addon-auth-api-key
Requires-Dist: odoo13-addon-queue-job
Requires-Dist: odoo13-addon-sale-order-import-ubl
Requires-Dist: odoo (<13.1dev,>=13.0a)
